src/__init__.py
src/constants.py
src/main.py
src/plots.py
src/simulation.py
src/utils.py
dropletevaporationsimulation-1.1.43.dist-info/METADATA
dropletevaporationsimulation-1.1.43.dist-info/WHEEL
dropletevaporationsimulation-1.1.43.dist-info/entry_points.txt
dropletevaporationsimulation-1.1.43.dist-info/top_level.txt
dropletevaporationsimulation-1.1.43.dist-info/RECORD
