Metadata-Version: 2.1
Name: dropletevaporationsimulation
Version: 1.1.43
Summary: This project simulates the evaporation and dynamics of an n-Decane droplet in a heated airflow.
Home-page: https://github.com/guillaume-bailly/DropletEvaporationSimulation
Author: Guillaume Bailly
Author-email: guillaume.bailly@estaca.eu
Classifier: Programming Language :: Python :: 3
Classifier: Operating System :: OS Independent
Requires-Python: >=3.11
Requires-Dist: numpy>=1.21.0
Requires-Dist: matplotlib>=3.4.0
Requires-Dist: scipy>=1.7.0
